genlayer_test-2.2.0.dist-info/licenses/LICENSE
gltest/__init__.py
gltest/accounts.py
gltest/assertions.py
gltest/clients.py
gltest/exceptions.py
gltest/fixtures.py
gltest/logging.py
gltest/types.py
gltest/artifacts/__init__.py
gltest/artifacts/contract.py
gltest/contracts/__init__.py
gltest/contracts/contract.py
gltest/contracts/contract_factory.py
gltest/contracts/contract_functions.py
gltest/contracts/method_stats.py
gltest/contracts/stats_collector.py
gltest/contracts/utils.py
gltest/helpers/__init__.py
gltest/helpers/fixture_snapshot.py
gltest/helpers/take_snapshot.py
gltest_cli/logging.py
gltest_cli/main.py
gltest_cli/config/__init__.py
gltest_cli/config/constants.py
gltest_cli/config/general.py
gltest_cli/config/plugin.py
gltest_cli/config/pytest_context.py
gltest_cli/config/types.py
gltest_cli/config/user.py
tests/__init__.py
tests/conftest.py
tests/examples/contracts/football_prediction_market.py
tests/examples/contracts/intelligent_oracle.py
tests/examples/contracts/intelligent_oracle_factory.py
tests/examples/contracts/llm_erc20.py
tests/examples/contracts/log_indexer.py
tests/examples/contracts/multi_read_erc20.py
tests/examples/contracts/multi_tenant_storage.py
tests/examples/contracts/read_erc20.py
tests/examples/contracts/storage.py
tests/examples/contracts/user_storage.py
tests/examples/contracts/wizard_of_coin.py
tests/examples/contracts/multi_file_contract/__init__.py
tests/examples/contracts/multi_file_contract/other.py
tests/examples/tests/test_football_prediction_market.py
tests/examples/tests/test_intelligent_oracle_factory.py
tests/examples/tests/test_llm_erc20.py
tests/examples/tests/test_llm_erc20_analyze.py
tests/examples/tests/test_log_indexer.py
tests/examples/tests/test_multi_file_contract.py
tests/examples/tests/test_multi_file_contract_legacy.py
tests/examples/tests/test_multi_read_erc20.py
tests/examples/tests/test_multi_tenant_storage.py
tests/examples/tests/test_read_erc20.py
tests/examples/tests/test_storage.py
tests/examples/tests/test_storage_legacy.py
genlayer_test-2.2.0.dist-info/METADATA
genlayer_test-2.2.0.dist-info/WHEEL
genlayer_test-2.2.0.dist-info/entry_points.txt
genlayer_test-2.2.0.dist-info/top_level.txt
genlayer_test-2.2.0.dist-info/RECORD
