Metadata-Version: 2.4
Name: genlayer-test
Version: 2.2.0
Summary: GenLayer Testing Suite
Author: GenLayer
License-Expression: MIT
Classifier: Development Status :: 4 - Beta
Classifier: Intended Audience :: Developers
Classifier: Programming Language :: Python :: 3
Classifier: Programming Language :: Python :: 3.12
Classifier: Programming Language :: Python :: 3.13
Classifier: Topic :: Software Development :: Testing
Requires-Python: >=3.12
License-File: LICENSE
Requires-Dist: pytest
Requires-Dist: setuptools>=77.0
Requires-Dist: genlayer-py==0.7.2
Requires-Dist: colorama>=0.4.6
Requires-Dist: pyyaml
Requires-Dist: python-dotenv
Dynamic: license-file
